{
	"info": {
		"_postman_id": "0969a09e-f484-4409-9ebf-bdc091fbc0c2",
		"name": "springboot-search-restapi",
		"schema": "https://schema.getpostman.com/json/collection/v2.1.0/collection.json",
		"_exporter_id": "27710072"
	},
	"item": [
		{
			"name": "createProduct",
			"request": {
				"method": "POST",
				"header": [],
				"body": {
					"mode": "raw",
					"raw": "{   \r\n    \"active\":true,\r\n    \"description\":\"laptopASUS description\",\r\n    \"imageUrl\":\"laptopASUS.png\",\r\n    \"name\":\"laptopASUS\",\r\n     \"sku\":\"ABCD\"\r\n}\r\n\r\n",
					"options": {
						"raw": {
							"language": "json"
						}
					}
				},
				"url": {
					"raw": "http://localhost:8080/api/v1/products",
					"protocol": "http",
					"host": [
						"localhost"
					],
					"port": "8080",
					"path": [
						"api",
						"v1",
						"products"
					]
				}
			},
			"response": []
		},
		{
			"name": "searchProduct",
			"request": {
				"method": "GET",
				"header": []
			},
			"response": []
		}
	]
}